PythonColouring/PythonColouring.py
PythonColouring/__init__.py
PythonColouring/h.py
PythonColouring/setup.py
PythonColouring-0.1.dist-info/METADATA
PythonColouring-0.1.dist-info/WHEEL
PythonColouring-0.1.dist-info/top_level.txt
PythonColouring-0.1.dist-info/RECORD
