Metadata-Version: 2.1
Name: PythonColouring
Version: 0.1
Summary: A module used to get colours to use in the Python terminal
Home-page: UNKNOWN
Author: CoolJames1610
Author-email: jadokofie@gmail.com
License: UNKNOWN
Keywords: PYTHON,COLOURING,TERMINAL,COLORED,PRINT,STYLE,COLORS,COLOURS
Platform: UNKNOWN
Classifier: Programming Language :: Python :: 3
Classifier: License :: OSI Approved :: MIT License
Classifier: Operating System :: OS Independent
Requires-Python: >=3.6
